sbvar/__init__.py
sbvar/io.py
sbvar/plotting.py
sbvar/timeseries.py
sbvar/utils.py
sbvar/experiment/__init__.py
sbvar/experiment/base.py
sbvar/experiment/one_way.py
sbvar/experiment/two_way.py
sbvar-1.0.0.dist-info/LICENSE
sbvar-1.0.0.dist-info/METADATA
sbvar-1.0.0.dist-info/WHEEL
sbvar-1.0.0.dist-info/top_level.txt
sbvar-1.0.0.dist-info/RECORD
